fairlex/__init__.py
fairlex/calibration.py
fairlex/metrics.py
fairlex/py.typed
fairlex-0.3.0.dist-info/WHEEL
fairlex-0.3.0.dist-info/METADATA
fairlex-0.3.0.dist-info/RECORD
