Metadata-Version: 2.3
Name: fairlex
Version: 0.3.0
Summary: Leximin calibration for survey weights
Author: Gaurav Sood
Author-email: Gaurav Sood <contact@gsood.com>
License: MIT
Classifier: Development Status :: 3 - Alpha
Classifier: License :: OSI Approved :: MIT License
Classifier: Programming Language :: Python
Classifier: Programming Language :: Python :: 3
Classifier: Programming Language :: Python :: 3 :: Only
Classifier: Programming Language :: Python :: 3.12
Classifier: Programming Language :: Python :: 3.13
Classifier: Programming Language :: Python :: 3.14
Classifier: Intended Audience :: Science/Research
Classifier: Topic :: Scientific/Engineering :: Mathematics
Classifier: Topic :: Scientific/Engineering :: Information Analysis
Requires-Dist: numpy>=1.26.0
Requires-Dist: scipy>=1.11.0
Requires-Python: >=3.12
Project-URL: Bug Tracker, https://github.com/finite-sample/fairlex/issues
Project-URL: Homepage, https://github.com/finite-sample/fairlex
Project-URL: Repository, https://github.com/finite-sample/fairlex
